Metadata-Version: 1.0
Name: nl-nut-telegraf
Version: 0.0.3
Summary: Basic NUT Data Exporter for Telegraf
Home-page: UNKNOWN
Author: nonlogicaldev
Author-email: UNKNOWN
License: UNKNOWN
Platform: UNKNOWN
